.DS_Store
ptas_unittest/index.py
ptas_unittest-1.0.2.dist-info/METADATA
ptas_unittest-1.0.2.dist-info/WHEEL
ptas_unittest-1.0.2.dist-info/top_level.txt
ptas_unittest-1.0.2.dist-info/RECORD
