Metadata-Version: 2.1
Name: ptas-unittest
Version: 1.0.2
Summary: PTAS Unittest
Home-page: UNKNOWN
Author: Hyegeun Choi
Author-email: hyegeun.c@nsensecorp.com
License: MIT
Platform: UNKNOWN
Requires-Python: >=3
